src/__main__.py
src/app.py
spotify_playlist_generator-0.0.2.dist-info/METADATA
spotify_playlist_generator-0.0.2.dist-info/WHEEL
spotify_playlist_generator-0.0.2.dist-info/entry_points.txt
spotify_playlist_generator-0.0.2.dist-info/top_level.txt
spotify_playlist_generator-0.0.2.dist-info/RECORD
