Metadata-Version: 2.1
Name: spotify-playlist-generator
Version: 0.0.2
Summary: Analyze your spotify playlists songs and create playlist with new songs
Home-page: https://github.com/murillo94/spotify-playlist-generator
Author: Murillo de Miranda Pereira
Author-email: murillomir0@gmail.com
License: MIT
Keywords: spotify playlist generator
Platform: UNKNOWN
Requires-Dist: spotipy
Requires-Dist: click
Requires-Dist: tqdm
